README.md
setup.py
stockquant/__init__.py
stockquant/backtest.py
stockquant/config.py
stockquant/indicators.py
stockquant/market.py
stockquant/quant.py
stockquant/tick.py
stockquant/source/__init__.py
stockquant/source/baostockdata.py
stockquant/source/sinadata.py
stockquant/source/tusharedata.py
stockquant/utils/__init__.py
stockquant/utils/dingtalk.py
stockquant/utils/logger.py
stockquant/utils/sendmail.py
stockquant/utils/storage.py
stockquant/utils/tools.py
stockquant_simple.egg-info/PKG-INFO
stockquant_simple.egg-info/SOURCES.txt
stockquant_simple.egg-info/dependency_links.txt
stockquant_simple.egg-info/requires.txt
stockquant_simple.egg-info/top_level.txt