Metadata-Version: 1.0
Name: stockquant-simple
Version: 0.3.0
Summary: Professional quant framework
Home-page: https://github.com/Gary-Hertel/StockQuant_simple
Author: Gary-Hertel
Author-email: hertelquant@foxmail.com
License: MIT
Keywords: stocklquant,quant,framework
Platform: any
